{
	"name": "DS_FILE_CHECK",
	"properties": {
		"linkedServiceName": {
			"referenceName": "LS_FILE_CHECK",
			"type": "LinkedServiceReference"
		},
		"annotations": [],
		"type": "DelimitedText",
		"typeProperties": {
			"location": {
				"type": "AzureBlobStorageLocation",
				"container": "inputcsv"
			},
			"columnDelimiter": ",",
			"escapeChar": "\\",
			"firstRowAsHeader": true,
			"quoteChar": "\""
		},
		"schema": [
			{
				"name": "SIC_Code",
				"type": "String"
			},
			{
				"name": "Description",
				"type": "String"
			}
		]
	},
	"type": "Microsoft.DataFactory/factories/datasets"
}