{
	"name": "LS_SP_WATERMARK",
	"properties": {
		"annotations": [],
		"type": "SqlServer",
		"typeProperties": {
			"server": "LAPTOP-SHRV1M0L\\SQLEXPRESS",
			"database": "RETAILDW_DEV",
			"encrypt": "mandatory",
			"trustServerCertificate": true,
			"authenticationType": "Windows",
			"userName": "LAPTOP-SHRV1M0L\\KSAURAV-95",
			"password": {
				"type": "AzureKeyVaultSecret",
				"store": {
					"referenceName": "AzureKeyVault1",
					"type": "LinkedServiceReference"
				},
				"secretName": "password"
			}
		},
		"connectVia": {
			"referenceName": "integrationRuntime1",
			"type": "IntegrationRuntimeReference"
		}
	}
}